dotfiles_cli/__init__.py
dotfiles_cli/cli.py
dotfiles_cli-0.2.4.dist-info/METADATA
dotfiles_cli-0.2.4.dist-info/WHEEL
dotfiles_cli-0.2.4.dist-info/entry_points.txt
dotfiles_cli-0.2.4.dist-info/RECORD
