Metadata-Version: 2.4
Name: dotfiles-cli
Version: 0.2.4
Summary: CLI tool to sync and manage dotfiles across machines
Project-URL: Homepage, https://github.com/FlynnOConnell/dotfiles-cli
Project-URL: Repository, https://github.com/FlynnOConnell/dotfiles-cli
Author-email: Flynn OConnell <flynnoconnell@gmail.com>
License-Expression: MIT
Keywords: cli,configuration,dotfiles,sync
Classifier: Development Status :: 4 - Beta
Classifier: Environment :: Console
Classifier: Intended Audience :: Developers
Classifier: License :: OSI Approved :: MIT License
Classifier: Operating System :: OS Independent
Classifier: Programming Language :: Python :: 3
Classifier: Programming Language :: Python :: 3.10
Classifier: Programming Language :: Python :: 3.11
Classifier: Programming Language :: Python :: 3.12
Classifier: Topic :: System :: Systems Administration
Classifier: Topic :: Utilities
Requires-Python: >=3.10
Requires-Dist: click>=8.0
Requires-Dist: rich>=13.0
Provides-Extra: dev
Requires-Dist: pytest>=7.0; extra == 'dev'
Requires-Dist: ruff>=0.1; extra == 'dev'
